daomodel-0.8.3b0.dist-info/METADATA
daomodel-0.8.3b0.dist-info/WHEEL
daomodel-0.8.3b0.dist-info/entry_points.txt
daomodel/__init__.py
daomodel/backwards_compatibility.py
daomodel/base_service.py
daomodel/change_set.py
daomodel/dao.py
daomodel/db.py
daomodel/fields.py
daomodel/list_util.py
daomodel/metaclass.py
daomodel/model_diff.py
daomodel/property_filter.py
daomodel/search_util.py
daomodel/testing.py
daomodel/transaction.py
daomodel/util.py
daomodel-0.8.3b0.dist-info/RECORD
