Metadata-Version: 2.1
Name: DAOModel
Version: 0.8.3b0
Summary: Provides an automatic DAO layer for your models
Keywords: dao,crud,model,database,db,search,query,sql,sqlmodel,sqlalchemy,pydantic
Author-Email: Cody M Sommer <bassmastacod@gmail.com>
License: MIT
Classifier: License :: OSI Approved :: MIT License
Classifier: Programming Language :: Python :: 3.10
Classifier: Programming Language :: Python :: 3.11
Classifier: Programming Language :: Python :: 3.12
Classifier: Programming Language :: Python :: 3.13
Classifier: Programming Language :: Python :: 3.14
Classifier: Development Status :: 4 - Beta
Classifier: Intended Audience :: Developers
Classifier: Topic :: Software Development :: Libraries
Classifier: Typing :: Typed
Project-URL: ReadTheDocs, https://daomodel.readthedocs.io/
Project-URL: Repository, https://github.com/BassMastaCod/DAOModel.git
Project-URL: Issues, https://github.com/BassMastaCod/DAOModel/issues
Requires-Python: >=3.10
Requires-Dist: sqlalchemy
Requires-Dist: sqlmodel
Requires-Dist: str_case_util
